MANIFEST.in
README.md
setup.cfg
setup.py
pyechonest/__init__.py
pyechonest/artist.py
pyechonest/catalog.py
pyechonest/config.py
pyechonest/playlist.py
pyechonest/proxies.py
pyechonest/sandbox.py
pyechonest/song.py
pyechonest/track.py
pyechonest/util.py
pyechonest.egg-info/PKG-INFO
pyechonest.egg-info/SOURCES.txt
pyechonest.egg-info/dependency_links.txt
pyechonest.egg-info/top_level.txt