Metadata-Version: 1.1
Name: pyechonest
Version: 9.0.0
Summary: Python interface to The Echo Nest APIs.
Home-page: https://github.com/echonest/pyechonest
Author: David DesRoches
Author-email: delicious@echonest.com
License: UNKNOWN
Download-URL: https://github.com/echonest/pyechonest
Platform: UNKNOWN
Requires: urllib
Requires: urllib2
Requires: json
